MANIFEST.in
README.txt
setup.cfg
setup.py
docs/HISTORY.txt
docs/INSTALL.txt
docs/LICENSE.GPL
docs/LICENSE.txt
redomino/__init__.py
redomino/__init__.pyc
redomino.cache.egg-info/PKG-INFO
redomino.cache.egg-info/SOURCES.txt
redomino.cache.egg-info/dependency_links.txt
redomino.cache.egg-info/entry_points.txt
redomino.cache.egg-info/namespace_packages.txt
redomino.cache.egg-info/not-zip-safe
redomino.cache.egg-info/requires.txt
redomino.cache.egg-info/top_level.txt
redomino/cache/__init__.py
redomino/cache/configure.zcml
redomino/cache/tests.py
redomino/cache/version.txt
redomino/cache/profiles/default/metadata.xml
redomino/cache/profiles/default/registry.xml