Metadata-Version: 1.0
Name: redomino.cache
Version: 0.1
Summary: 'Plone app caching preconfigured'
Home-page: https://github.com/redomino/redomino.cache
Author: Luca Cipriani
Author-email: luca.cipriani@redomino.com
License: GPL
Keywords: plone caching
Platform: UNKNOWN
Classifier: Framework :: Plone
Classifier: Programming Language :: Python
